codebeginsCalculator/__init__.py
codebeginsClaaculator-1.0.dist-info/LICENSE.txt
codebeginsClaaculator-1.0.dist-info/METADATA
codebeginsClaaculator-1.0.dist-info/WHEEL
codebeginsClaaculator-1.0.dist-info/top_level.txt
codebeginsClaaculator-1.0.dist-info/RECORD
