Metadata-Version: 2.1
Name: codebeginsClaaculator
Version: 1.0
Summary: A useful Calculator
Author: Atanu Mondal
Author-email: atanumondalbarjora@gmail.com
Classifier: Programming Language :: Python :: 3
Classifier: License :: OSI Approved :: MIT License
Classifier: Operating System :: OS Independent
License-File: LICENSE.txt
